{
	"image_text": {
		"src": "images/content/ali.jpg",
		"alt": "恒大股权变动！阿里降至40% 董事长轮值更换",
		"href": "javascript:void(0);"
	},
	"news": [
		{
			"title": "中超-正视频直播永昌vs鲁能 亚泰vs茅台",
			"href": "javascript:void(0);",
			"clas": "qvp"
		},
		[
			{
				"title": "女足世界杯八强全部产生",
				"href": "javascript:void(0);",
				"clas": ""
			},
			{
				"title": "李冬娜：90分钟解决美国",
				"href": "javascript:void(0);"
			}
		],
		{
			"title": "宗庆后震惊女足球员月薪3000 当即决定奖100万",
			"href": "javascript:void(0);"
		},
		{
			"title": "热身赛-正图文直播中国男篮vs立陶宛 易建联出战",
			"href": "javascript:void(0);"
		},
		{
			"title": "湖人试训80人 榜眼签3选1？",
			"href": "javascript:void(0);"
		},
		[
			{
				"title": "美洲杯夺冠赔率：智利压巴西",
				"href": "javascript:void(0);"
			},
			{
				"title": "巴西国脚加盟利物浦",
				"href": "javascript:void(0);"
			}
		]
	],
	"newsRight": [
		{
			"title": "【锐评】跪艾弗森不如“跪”市场",
			"href": "javascript:void(0);",
			"clas": ""
		},
		{
			"title": "霸气！中国揽第14届军警狙击手世界杯全部冠军",
			"href": "javascript:void(0);",
			"clas": ""
		},
		{
			"title": "美女体育记者转行当女优 自曝与多名选手上床",
			"href": "javascript:void(0);",
			"clas": ""
		},
		{
			"title": "恒大足校获颁吉尼斯“最大寄宿制足球学校”",
			"href": "javascript:void(0);",
			"clas": " qvp "
		},
		{
			"title": "丁俊晖谈被大逆转输球：那感觉就像丢了1个亿",
			"href": "javascript:void(0);",
			"clas": ""
		},
		{
			"title": "骑士执行莫兹戈夫球队选项 强力内线再助詹皇",
			"href": "javascript:void(0);",
			"clas": " qpp "
		},
		{
			"title": "曝巴萨敲定博格巴加盟 全欧垂涎之人明夏来投",
			"href": "javascript:void(0);",
			"clas": " qpp "
		},
		{
			"title": "蓝军总价6500万欧追马竞头牌 萨拉赫将成添头",
			"href": "javascript:void(0);",
			"clas": " qpp "
		},
		{
			"title": "“晒”出男人味！肤色全变 C罗：已无需再黑",
			"href": "javascript:void(0);",
			"clas": " qvp "
		}
	]
}